dxs-0.1.0.dev2520.dist-info/METADATA
dxs-0.1.0.dev2520.dist-info/WHEEL
dxs-0.1.0.dev2520.dist-info/entry_points.txt
dxs-0.1.0.dev2520.dist-info/licenses/LICENSE
dxs/__init__.py
dxs/main.py
dxs/templates/.gitignore
dxs/templates/LICENSE
dxs/templates/README.md
dxs/templates/src/__init__.py
dxs/templates/test/main.py
dxs-0.1.0.dev2520.dist-info/RECORD
