Metadata-Version: 2.1
Name: dxs
Version: 0.1.0.dev2520
Summary: Cli tool to create a project structure.
Keywords: dxs cli dxs cli
Author-Email: Daxexs <Daxexsdev@gmail.com>
License: apache-2.0
Classifier: Topic :: Software Development :: Build Tools
Classifier: Programming Language :: Python :: 3.8
Classifier: Programming Language :: Python :: 3.9
Classifier: Programming Language :: Python :: 3.10
Classifier: Programming Language :: Python :: 3.11
Classifier: Programming Language :: Python :: 3.12
Project-URL: Homepage, https://github.com/Daxexs
Project-URL: Repository, https://github.com/Daxexs/dxs
Project-URL: Documentation, https://github.com/Daxexs/dxs/blob/main/README.md
Project-URL: Changelog, https://github.com/Daxexs/dxs/blob/main/README.md
Requires-Python: >=3.8
Requires-Dist: typer[all]
Requires-Dist: toml
Requires-Dist: twine
Requires-Dist: build
